{
  "project_info": {
    "project_number": "720193141595",
    "project_id": "psychologyapp-148702"
  },
  "client": [
    {
      "client_info": {
        "mobilesdk_app_id": "1:720193141595:android:e5bb7edcca8cf8df",
        "android_client_info": {
          "package_name": "com.example.wad.ups"
        }
      },
      "oauth_client": [],
      "api_key": [
        {
          "current_key": "AIzaSyCS0kE7iHFl1Rk6owf0r_izcRbHFBgXVWg"
        }
      ],
      "services": {
        "analytics_service": {
          "status": 1
        },
        "appinvite_service": {
          "status": 1,
          "other_platform_oauth_client": []
        },
        "ads_service": {
          "status": 1
        }
      }
    }
  ],
  "configuration_version": "1"
}